LICENSE
README.md
pyproject.toml
setup.py
src/MyToolbox/Toolbox.py
src/MyToolbox/__init__.py
src/tbxransaka.egg-info/PKG-INFO
src/tbxransaka.egg-info/SOURCES.txt
src/tbxransaka.egg-info/dependency_links.txt
src/tbxransaka.egg-info/top_level.txt