Metadata-Version: 2.1
Name: tbxransaka
Version: 0.0.1
Summary: My customized toolbox for dayly works.
Author: Ransaka
Author-email: ransakaravihara@gmail.com
License: UNKNOWN
Platform: UNKNOWN
Classifier: Programming Language :: Python :: 3
Classifier: License :: OSI Approved :: MIT License
Classifier: Operating System :: OS Independent
Requires-Python: >=3.6
License-File: LICENSE
